httpx_pkcs12/__init__.py
httpx_pkcs12-2.0.0.dist-info/METADATA
httpx_pkcs12-2.0.0.dist-info/WHEEL
httpx_pkcs12-2.0.0.dist-info/licenses/LICENSE
httpx_pkcs12-2.0.0.dist-info/RECORD
