Metadata-Version: 2.4
Name: httpx_pkcs12
Version: 2.0.0
Summary: Addon which activates PKCS12 certificates usage with HTTPX client.
Project-URL: Repository, https://github.com/theLastOfCats/httpx-pkcs12.git
Author-email: Shagit Ziganshin <theLastOfCats@duck.com>
License: MIT
License-File: LICENSE
Keywords: httpx,pkcs12,ssl
Classifier: Development Status :: 5 - Production/Stable
Classifier: Intended Audience :: Developers
Classifier: Programming Language :: Python :: 3
Classifier: Programming Language :: Python :: 3.10
Classifier: Programming Language :: Python :: 3.11
Classifier: Programming Language :: Python :: 3.12
Classifier: Programming Language :: Python :: 3.13
Classifier: Topic :: Software Development :: Build Tools
Requires-Python: >=3.10
Requires-Dist: cryptography>=44.0.1
Provides-Extra: dev
Requires-Dist: httpx>=0.24.0; extra == 'dev'
Requires-Dist: mypy>=1.8.0; extra == 'dev'
Requires-Dist: pytest-cov>=4.0.0; extra == 'dev'
Requires-Dist: pytest>=7.0.0; extra == 'dev'
Requires-Dist: ruff>=0.3.0; extra == 'dev'
